mystepuppack/__init__.py
mystepuppack/arth.py
mystepuppack/title.py
mystepuppack-3.0.dist-info/METADATA
mystepuppack-3.0.dist-info/WHEEL
mystepuppack-3.0.dist-info/top_level.txt
mystepuppack-3.0.dist-info/RECORD
