Metadata-Version: 2.1
Name: mystepuppack
Version: 3.0
Summary: My first Python library
Home-page: UNKNOWN
Author: StepUp
License: MIT
Platform: UNKNOWN
